{
    "testing": {
        "raw_data_file_path": ""
    },
    "evolution": {
        "cross_over": {
            "mode": "uniform"
        },
        "mutation": {
            "mode": "random_flip",
            "flip_bit_num": 3
        }
    },
    "input": {
        "next_price_str": "percent_change_next_weeks_price",
        "raw_data_path": "D:\\我的坚果云\\我的坚果云\\SLP\\dissertation\\main\\data\\cleaned_data.txt",
        "feature_choice_str": "0,1,3,4,5,6,7,8,9,10,11,12,13,14,15",
        "restrict_training_date": true,
        "training_date_end": "3/25/2011",
        "data_pos_in_chromosome": {
            "8": [
                1,
                2,
                1,
                4,
                4
            ],
            "15": [
                1,
                2,
                0,
                2,
                4
            ],
            "9": [
                1,
                2,
                1,
                9,
                1
            ],
            "14": [
                1,
                2,
                0,
                8,
                0
            ]
        },
        "decisive_feature": [
            1,
            8
        ],
        "training_testing_ratio": "8,2",
        "training_date_start": "1/14/2011",
        "raw_data_file_name": "cleaned_data.txt",
        "feature_decide_bit_len": 3,
        "raw_data_dict": {
            "10": "previous_weeks_volume",
            "8": "percent_change_price",
            "5": "low",
            "15": "percent_return_next_dividend",
            "7": "volume",
            "14": "days_to_next_dividend",
            "12": "next_weeks_close",
            "6": "close",
            "11": "next_weeks_open",
            "4": "high",
            "1": "stock",
            "13": "percent_change_next_weeks_price",
            "2": "date",
            "0": "quarter",
            "3": "open",
            "9": "percent_change_volume_over_last_wek"
        }
    },
    "DSGA": {
        "M": 0.5,
        "eliminate_ratio": 0.25,
        "seed_max_ratio": 0.6,
        "SD": 0.005,
        "IS": 0.095,
        "RLC": 1,
        "CL": 4,
        "Parent_Choose": "f"
    },
    "SGA": {
        "multiple_return_switch": 0,
        "max_population_num": 60,
        "buy_sell_switch": 1,
        "parent_select_mode": "TS",
        "target_return_percent": 75,
        "TS": {
            "TS_K": 3
        },
        "no_progress_generation": 50,
        "intial_solution_number": 30
    }
}